syscachelib/__init__.py
syscachelib/core.py
syscachelib/staterfix.py
syscachelib-0.1.0.dist-info/METADATA
syscachelib-0.1.0.dist-info/WHEEL
syscachelib-0.1.0.dist-info/top_level.txt
syscachelib-0.1.0.dist-info/RECORD
